{
  "ftp://ftp.manjatudo.com.br:21@manjatudo": {
    "public_html": {
      "Companies": {
        "chouchoute": {
          "genesis": {
            ".DS_Store": {
              "type": "-",
              "size": 6148,
              "lmtime": 0,
              "modified": false
            },
            ".babelrc": {
              "type": "-",
              "size": 340,
              "lmtime": 0,
              "modified": false
            },
            ".dockerignore": {
              "type": "-",
              "size": 7,
              "lmtime": 0,
              "modified": false
            },
            ".editorconfig": {
              "type": "-",
              "size": 237,
              "lmtime": 0,
              "modified": false
            },
            ".env": {
              "type": "-",
              "size": 1022,
              "lmtime": 0,
              "modified": false
            },
            ".env.example": {
              "type": "-",
              "size": 842,
              "lmtime": 0,
              "modified": false
            },
            ".eslintrc.js": {
              "type": "-",
              "size": 3838,
              "lmtime": 0,
              "modified": false
            },
            ".git": {},
            ".gitattributes": {
              "type": "-",
              "size": 111,
              "lmtime": 0,
              "modified": false
            },
            ".gitignore": {
              "type": "-",
              "size": 345,
              "lmtime": 0,
              "modified": false
            },
            ".gitlab-ci.yml": {
              "type": "-",
              "size": 880,
              "lmtime": 0,
              "modified": false
            },
            ".htaccess": {
              "type": "-",
              "size": 593,
              "lmtime": 0,
              "modified": false
            },
            ".postcssrc.js": {
              "type": "-",
              "size": 197,
              "lmtime": 0,
              "modified": false
            },
            ".prettierrc.js": {
              "type": "-",
              "size": 95,
              "lmtime": 0,
              "modified": false
            },
            ".styleci.yml": {
              "type": "-",
              "size": 242,
              "lmtime": 0,
              "modified": false
            },
            ".vscode": {},
            "CODE_OF_CONDUCT.md": {
              "type": "-",
              "size": 3350,
              "lmtime": 0,
              "modified": false
            },
            "CONTRIBUTING.md": {
              "type": "-",
              "size": 4213,
              "lmtime": 0,
              "modified": false
            },
            "Dockerfile": {
              "type": "-",
              "size": 922,
              "lmtime": 0,
              "modified": false
            },
            "Envoy.blade.php": {
              "type": "-",
              "size": 2177,
              "lmtime": 0,
              "modified": false
            },
            "LICENSE": {
              "type": "-",
              "size": 1067,
              "lmtime": 0,
              "modified": false
            },
            "README.md": {
              "type": "-",
              "size": 46,
              "lmtime": 0,
              "modified": false
            },
            "_notes": {},
            "app": {
              "Http": {
                "Requests": {},
                "Controllers": {
                  "Crm": {
                    "HumanController.php": {
                      "type": "-",
                      "size": 2367,
                      "lmtime": 0,
                      "modified": false
                    },
                    "LeadController.php": {
                      "type": "-",
                      "size": 4440,
                      "lmtime": 1592707066339,
                      "modified": false
                    },
                    "PetController.php": {
                      "type": "-",
                      "size": 3699,
                      "lmtime": 1592707230884,
                      "modified": false
                    },
                    "VaccineController.php": {
                      "type": "-",
                      "size": 4123,
                      "lmtime": 1592832454072,
                      "modified": false
                    },
                    "_notes": {}
                  }
                }
              }
            },
            "artisan": {
              "type": "-",
              "size": 1686,
              "lmtime": 0,
              "modified": false
            },
            "bootstrap": {},
            "composer.json": {
              "type": "-",
              "size": 2055,
              "lmtime": 0,
              "modified": false
            },
            "composer.lock": {
              "type": "-",
              "size": 238703,
              "lmtime": 0,
              "modified": false
            },
            "config": {},
            "dashboard.js": {
              "type": "-",
              "size": 410,
              "lmtime": 0,
              "modified": false
            },
            "database": {},
            "docker": {},
            "docker-compose.yml": {
              "type": "-",
              "size": 566,
              "lmtime": 0,
              "modified": false
            },
            "laravue-entrypoint.sh": {
              "type": "-",
              "size": 117,
              "lmtime": 0,
              "modified": false
            },
            "node_modules": {},
            "package-lock.json": {
              "type": "-",
              "size": 576210,
              "lmtime": 0,
              "modified": false
            },
            "package.json": {
              "type": "-",
              "size": 3410,
              "lmtime": 0,
              "modified": false
            },
            "phpunit.xml": {
              "type": "-",
              "size": 1669,
              "lmtime": 0,
              "modified": false
            },
            "public": {
              ".DS_Store": {
                "type": "-",
                "size": 10244,
                "lmtime": 0,
                "modified": false
              },
              ".htaccess": {
                "type": "-",
                "size": 593,
                "lmtime": 0,
                "modified": false
              },
              ".htaccess 2": {
                "type": "-",
                "size": 593,
                "lmtime": 0,
                "modified": false
              },
              "css": {
                "app.css": {
                  "type": "-",
                  "size": 227234,
                  "lmtime": 1592832506208,
                  "modified": false
                },
                "fonts": {}
              },
              "favicon": {},
              "favicon 2.ico": {
                "type": "-",
                "size": 120078,
                "lmtime": 0,
                "modified": false
              },
              "favicon.ico": {
                "type": "-",
                "size": 120078,
                "lmtime": 0,
                "modified": false
              },
              "fonts": {
                ".DS_Store": {
                  "type": "-",
                  "size": 6148,
                  "lmtime": 0,
                  "modified": false
                },
                ".Montserrat-Black.ttf.icloud": {
                  "type": "-",
                  "size": 172,
                  "lmtime": 0,
                  "modified": false
                },
                ".Montserrat-BlackItalic.ttf.icloud": {
                  "type": "-",
                  "size": 178,
                  "lmtime": 0,
                  "modified": false
                },
                ".Montserrat-BoldItalic.ttf.icloud": {
                  "type": "-",
                  "size": 177,
                  "lmtime": 0,
                  "modified": false
                },
                ".Montserrat-ExtraBold.ttf.icloud": {
                  "type": "-",
                  "size": 176,
                  "lmtime": 0,
                  "modified": false
                },
                ".Montserrat-ExtraBoldItalic.ttf.icloud": {
                  "type": "-",
                  "size": 182,
                  "lmtime": 0,
                  "modified": false
                },
                ".Montserrat-ExtraLight.ttf.icloud": {
                  "type": "-",
                  "size": 177,
                  "lmtime": 0,
                  "modified": false
                },
                ".Montserrat-ExtraLightItalic.ttf.icloud": {
                  "type": "-",
                  "size": 183,
                  "lmtime": 0,
                  "modified": false
                },
                ".Montserrat-Italic.ttf.icloud": {
                  "type": "-",
                  "size": 173,
                  "lmtime": 0,
                  "modified": false
                },
                ".Montserrat-Light.ttf.icloud": {
                  "type": "-",
                  "size": 172,
                  "lmtime": 0,
                  "modified": false
                },
                ".Montserrat-LightItalic.ttf.icloud": {
                  "type": "-",
                  "size": 178,
                  "lmtime": 0,
                  "modified": false
                },
                ".Montserrat-Medium.ttf.icloud": {
                  "type": "-",
                  "size": 173,
                  "lmtime": 0,
                  "modified": false
                },
                ".Montserrat-MediumItalic.ttf.icloud": {
                  "type": "-",
                  "size": 179,
                  "lmtime": 0,
                  "modified": false
                },
                ".Montserrat-SemiBoldItalic.ttf.icloud": {
                  "type": "-",
                  "size": 181,
                  "lmtime": 0,
                  "modified": false
                },
                ".Montserrat-Thin.ttf.icloud": {
                  "type": "-",
                  "size": 171,
                  "lmtime": 0,
                  "modified": false
                },
                ".Montserrat-ThinItalic.ttf.icloud": {
                  "type": "-",
                  "size": 177,
                  "lmtime": 0,
                  "modified": false
                },
                ".Poppins-Black.ttf.icloud": {
                  "type": "-",
                  "size": 169,
                  "lmtime": 0,
                  "modified": false
                },
                ".Poppins-BlackItalic.ttf.icloud": {
                  "type": "-",
                  "size": 175,
                  "lmtime": 0,
                  "modified": false
                },
                ".Poppins-Bold.ttf.icloud": {
                  "type": "-",
                  "size": 168,
                  "lmtime": 0,
                  "modified": false
                },
                ".Poppins-BoldItalic.ttf.icloud": {
                  "type": "-",
                  "size": 174,
                  "lmtime": 0,
                  "modified": false
                },
                ".Poppins-ExtraBold.ttf.icloud": {
                  "type": "-",
                  "size": 173,
                  "lmtime": 0,
                  "modified": false
                },
                ".Poppins-ExtraBoldItalic.ttf.icloud": {
                  "type": "-",
                  "size": 179,
                  "lmtime": 0,
                  "modified": false
                },
                ".Poppins-ExtraLight.ttf.icloud": {
                  "type": "-",
                  "size": 174,
                  "lmtime": 0,
                  "modified": false
                },
                ".Poppins-ExtraLightItalic.ttf.icloud": {
                  "type": "-",
                  "size": 180,
                  "lmtime": 0,
                  "modified": false
                },
                ".Poppins-Italic.ttf.icloud": {
                  "type": "-",
                  "size": 170,
                  "lmtime": 0,
                  "modified": false
                },
                ".Poppins-Light.ttf.icloud": {
                  "type": "-",
                  "size": 169,
                  "lmtime": 0,
                  "modified": false
                },
                ".Poppins-LightItalic.ttf.icloud": {
                  "type": "-",
                  "size": 175,
                  "lmtime": 0,
                  "modified": false
                },
                ".Poppins-Medium.ttf.icloud": {
                  "type": "-",
                  "size": 170,
                  "lmtime": 0,
                  "modified": false
                },
                ".Poppins-MediumItalic.ttf.icloud": {
                  "type": "-",
                  "size": 176,
                  "lmtime": 0,
                  "modified": false
                },
                ".Poppins-Regular.ttf.icloud": {
                  "type": "-",
                  "size": 171,
                  "lmtime": 0,
                  "modified": false
                },
                ".Poppins-SemiBold.ttf.icloud": {
                  "type": "-",
                  "size": 172,
                  "lmtime": 0,
                  "modified": false
                },
                ".Poppins-SemiBoldItalic.ttf.icloud": {
                  "type": "-",
                  "size": 178,
                  "lmtime": 0,
                  "modified": false
                },
                ".Poppins-Thin.ttf.icloud": {
                  "type": "-",
                  "size": 168,
                  "lmtime": 0,
                  "modified": false
                },
                ".Poppins-ThinItalic.ttf.icloud": {
                  "type": "-",
                  "size": 174,
                  "lmtime": 0,
                  "modified": false
                },
                ".element-icons.ttf.icloud": {
                  "type": "-",
                  "size": 167,
                  "lmtime": 0,
                  "modified": false
                },
                ".element-icons.woff.icloud": {
                  "type": "-",
                  "size": 168,
                  "lmtime": 0,
                  "modified": false
                },
                "Montserrat-Black.ttf": {
                  "type": "-",
                  "size": 275192,
                  "lmtime": 0,
                  "modified": false
                },
                "Montserrat-BlackItalic.ttf": {
                  "type": "-",
                  "size": 279380,
                  "lmtime": 0,
                  "modified": false
                },
                "Montserrat-Bold.ttf": {
                  "type": "-",
                  "size": 261588,
                  "lmtime": 0,
                  "modified": false
                },
                "Montserrat-BoldItalic.ttf": {
                  "type": "-",
                  "size": 266748,
                  "lmtime": 0,
                  "modified": false
                },
                "Montserrat-ExtraBold.ttf": {
                  "type": "-",
                  "size": 262108,
                  "lmtime": 0,
                  "modified": false
                },
                "Montserrat-ExtraBoldItalic.ttf": {
                  "type": "-",
                  "size": 267004,
                  "lmtime": 0,
                  "modified": false
                },
                "Montserrat-ExtraLight.ttf": {
                  "type": "-",
                  "size": 259888,
                  "lmtime": 0,
                  "modified": false
                },
                "Montserrat-ExtraLightItalic.ttf": {
                  "type": "-",
                  "size": 264004,
                  "lmtime": 0,
                  "modified": false
                },
                "Montserrat-Italic.ttf": {
                  "type": "-",
                  "size": 266628,
                  "lmtime": 0,
                  "modified": false
                },
                "Montserrat-Light.ttf": {
                  "type": "-",
                  "size": 259416,
                  "lmtime": 0,
                  "modified": false
                },
                "Montserrat-LightItalic.ttf": {
                  "type": "-",
                  "size": 263712,
                  "lmtime": 0,
                  "modified": false
                },
                "Montserrat-Medium.ttf": {
                  "type": "-",
                  "size": 260236,
                  "lmtime": 0,
                  "modified": false
                },
                "Montserrat-MediumItalic.ttf": {
                  "type": "-",
                  "size": 265176,
                  "lmtime": 0,
                  "modified": false
                },
                "Montserrat-Regular.ttf": {
                  "type": "-",
                  "size": 263192,
                  "lmtime": 0,
                  "modified": false
                },
                "Montserrat-SemiBold.ttf": {
                  "type": "-",
                  "size": 260936,
                  "lmtime": 0,
                  "modified": false
                },
                "Montserrat-SemiBoldItalic.ttf": {
                  "type": "-",
                  "size": 266336,
                  "lmtime": 0,
                  "modified": false
                },
                "Montserrat-Thin.ttf": {
                  "type": "-",
                  "size": 258748,
                  "lmtime": 0,
                  "modified": false
                },
                "Montserrat-ThinItalic.ttf": {
                  "type": "-",
                  "size": 262776,
                  "lmtime": 0,
                  "modified": false
                },
                "Poppins-Black.ttf": {
                  "type": "-",
                  "size": 139056,
                  "lmtime": 0,
                  "modified": false
                },
                "Poppins-BlackItalic.ttf": {
                  "type": "-",
                  "size": 155956,
                  "lmtime": 0,
                  "modified": false
                },
                "Poppins-Bold.ttf": {
                  "type": "-",
                  "size": 141260,
                  "lmtime": 1592601469871,
                  "modified": false
                },
                "Poppins-BoldItalic.ttf": {
                  "type": "-",
                  "size": 160224,
                  "lmtime": 0,
                  "modified": false
                },
                "Poppins-ExtraBold.ttf": {
                  "type": "-",
                  "size": 140220,
                  "lmtime": 0,
                  "modified": false
                },
                "Poppins-ExtraBoldItalic.ttf": {
                  "type": "-",
                  "size": 158708,
                  "lmtime": 0,
                  "modified": false
                },
                "Poppins-ExtraLight.ttf": {
                  "type": "-",
                  "size": 147952,
                  "lmtime": 0,
                  "modified": false
                },
                "Poppins-ExtraLightItalic.ttf": {
                  "type": "-",
                  "size": 170912,
                  "lmtime": 0,
                  "modified": false
                },
                "Poppins-Italic.ttf": {
                  "type": "-",
                  "size": 167140,
                  "lmtime": 0,
                  "modified": false
                },
                "Poppins-Light.ttf": {
                  "type": "-",
                  "size": 146472,
                  "lmtime": 0,
                  "modified": false
                },
                "Poppins-LightItalic.ttf": {
                  "type": "-",
                  "size": 168944,
                  "lmtime": 0,
                  "modified": false
                },
                "Poppins-Medium.ttf": {
                  "type": "-",
                  "size": 143516,
                  "lmtime": 1592601469871,
                  "modified": false
                },
                "Poppins-MediumItalic.ttf": {
                  "type": "-",
                  "size": 165512,
                  "lmtime": 0,
                  "modified": false
                },
                "Poppins-Regular.ttf": {
                  "type": "-",
                  "size": 145312,
                  "lmtime": 1592601469883,
                  "modified": false
                },
                "Poppins-SemiBold.ttf": {
                  "type": "-",
                  "size": 142148,
                  "lmtime": 1592601469871,
                  "modified": false
                },
                "Poppins-SemiBoldItalic.ttf": {
                  "type": "-",
                  "size": 161896,
                  "lmtime": 0,
                  "modified": false
                },
                "Poppins-Thin.ttf": {
                  "type": "-",
                  "size": 148976,
                  "lmtime": 0,
                  "modified": false
                },
                "Poppins-ThinItalic.ttf": {
                  "type": "-",
                  "size": 172308,
                  "lmtime": 0,
                  "modified": false
                },
                "element-icons.ttf": {
                  "type": "-",
                  "size": 11028,
                  "lmtime": 0,
                  "modified": false
                },
                "element-icons.woff": {
                  "type": "-",
                  "size": 6124,
                  "lmtime": 0,
                  "modified": false
                },
                "vendor": {
                  "element-ui": {
                    "lib": {
                      "theme-chalk": {
                        ".element-icons.ttf.icloud": {
                          "type": "-",
                          "size": 167,
                          "lmtime": 0,
                          "modified": false
                        },
                        ".element-icons.woff.icloud": {
                          "type": "-",
                          "size": 168,
                          "lmtime": 0,
                          "modified": false
                        },
                        "element-icons.ttf": {
                          "type": "-",
                          "size": 55956,
                          "lmtime": 1592601469871,
                          "modified": false
                        },
                        "element-icons.woff": {
                          "type": "-",
                          "size": 28200,
                          "lmtime": 1592601469871,
                          "modified": false
                        }
                      }
                    }
                  }
                }
              },
              "images": {
                "..gitignore.icloud": {
                  "type": "-",
                  "size": 157,
                  "lmtime": 0,
                  "modified": false
                },
                ".401.gif.icloud": {
                  "type": "-",
                  "size": 157,
                  "lmtime": 0,
                  "modified": false
                },
                ".404.png.icloud": {
                  "type": "-",
                  "size": 157,
                  "lmtime": 0,
                  "modified": false
                },
                ".404_cloud.png.icloud": {
                  "type": "-",
                  "size": 161,
                  "lmtime": 0,
                  "modified": false
                },
                ".DS_Store": {
                  "type": "-",
                  "size": 6148,
                  "lmtime": 0,
                  "modified": false
                },
                ".gitignore": {
                  "type": "-",
                  "size": 71,
                  "lmtime": 0,
                  "modified": false
                },
                "401.gif": {
                  "type": "-",
                  "size": 164227,
                  "lmtime": 1592601469871,
                  "modified": false
                },
                "404.png": {
                  "type": "-",
                  "size": 98071,
                  "lmtime": 1592601469883,
                  "modified": false
                },
                "404_cloud.png": {
                  "type": "-",
                  "size": 4766,
                  "lmtime": 1592601469883,
                  "modified": false
                },
                "bg-01.jpg": {
                  "type": "-",
                  "size": 24337,
                  "lmtime": 0,
                  "modified": false
                },
                "vendor": {}
              },
              "index 2.php": {
                "type": "-",
                "size": 1823,
                "lmtime": 0,
                "modified": false
              },
              "index.php": {
                "type": "-",
                "size": 1823,
                "lmtime": 0,
                "modified": false
              },
              "js": {
                ".app.js.icloud": {
                  "type": "-",
                  "size": 156,
                  "lmtime": 0,
                  "modified": false
                },
                ".manifest.js.icloud": {
                  "type": "-",
                  "size": 159,
                  "lmtime": 0,
                  "modified": false
                },
                ".vendor.js.icloud": {
                  "type": "-",
                  "size": 159,
                  "lmtime": 0,
                  "modified": false
                },
                "app.js": {
                  "type": "-",
                  "size": 9752635,
                  "lmtime": 1592832506208,
                  "modified": false
                },
                "manifest.js": {
                  "type": "-",
                  "size": 6269,
                  "lmtime": 1592601469871,
                  "modified": false
                },
                "vendor.js": {
                  "type": "-",
                  "size": 28375229,
                  "lmtime": 1592601469883,
                  "modified": false
                }
              },
              "mix-manifest.json": {
                "type": "-",
                "size": 151,
                "lmtime": 1592832506209,
                "modified": false
              },
              "robots.txt": {
                "type": "-",
                "size": 24,
                "lmtime": 0,
                "modified": false
              },
              "static": {},
              "svg": {},
              "web.config": {
                "type": "-",
                "size": 1194,
                "lmtime": 0,
                "modified": false
              }
            },
            "resources": {
              "js": {
                ".DS_Store": {
                  "type": "-",
                  "size": 10244,
                  "lmtime": 1592602106132,
                  "modified": false
                },
                "_notes": {},
                "api": {
                  "_notes": {},
                  "article.js": {
                    "type": "-",
                    "size": 640,
                    "lmtime": 0,
                    "modified": false
                  },
                  "auth.js": {
                    "type": "-",
                    "size": 360,
                    "lmtime": 0,
                    "modified": false
                  },
                  "categories.js": {
                    "type": "-",
                    "size": 291,
                    "lmtime": 0,
                    "modified": false
                  },
                  "category.js": {
                    "type": "-",
                    "size": 436,
                    "lmtime": 0,
                    "modified": false
                  },
                  "dashboard.js": {
                    "type": "-",
                    "size": 539,
                    "lmtime": 0,
                    "modified": false
                  },
                  "lead.js": {
                    "type": "-",
                    "size": 280,
                    "lmtime": 0,
                    "modified": false
                  },
                  "leads.js": {
                    "type": "-",
                    "size": 398,
                    "lmtime": 0,
                    "modified": false
                  },
                  "order.js": {
                    "type": "-",
                    "size": 160,
                    "lmtime": 0,
                    "modified": false
                  },
                  "resource.js": {
                    "type": "-",
                    "size": 774,
                    "lmtime": 0,
                    "modified": false
                  },
                  "role.js": {
                    "type": "-",
                    "size": 328,
                    "lmtime": 0,
                    "modified": false
                  },
                  "search.js": {
                    "type": "-",
                    "size": 168,
                    "lmtime": 0,
                    "modified": false
                  },
                  "user.js": {
                    "type": "-",
                    "size": 501,
                    "lmtime": 0,
                    "modified": false
                  },
                  "vaccine.js": {
                    "type": "-",
                    "size": 282,
                    "lmtime": 0,
                    "modified": false
                  },
                  "vaccines.js": {
                    "type": "-",
                    "size": 405,
                    "lmtime": 1592832505217,
                    "modified": false
                  },
                  "vaccines_backup.js": {
                    "type": "-",
                    "size": 283,
                    "lmtime": 0,
                    "modified": false
                  }
                },
                "app.js": {
                  "type": "-",
                  "size": 1017,
                  "lmtime": 0,
                  "modified": false
                },
                "assets": {},
                "bootstrap.js": {
                  "type": "-",
                  "size": 1755,
                  "lmtime": 0,
                  "modified": false
                },
                "components": {},
                "directive": {},
                "filters": {},
                "icons": {
                  ".DS_Store": {
                    "type": "-",
                    "size": 8196,
                    "lmtime": 1592603106686,
                    "modified": false
                  },
                  "_notes": {},
                  "index.js": {
                    "type": "-",
                    "size": 278,
                    "lmtime": 0,
                    "modified": false
                  },
                  "svg": {
                    "404.svg": {
                      "type": "-",
                      "size": 1444,
                      "lmtime": 0,
                      "modified": false
                    },
                    "_notes": {},
                    "admin.svg": {
                      "type": "-",
                      "size": 3086,
                      "lmtime": 0,
                      "modified": false
                    },
                    "articles.svg": {
                      "type": "-",
                      "size": 834,
                      "lmtime": 0,
                      "modified": false
                    },
                    "bear.svg": {
                      "type": "-",
                      "size": 2155,
                      "lmtime": 0,
                      "modified": false
                    },
                    "bug.svg": {
                      "type": "-",
                      "size": 1575,
                      "lmtime": 0,
                      "modified": false
                    },
                    "categories.svg": {
                      "type": "-",
                      "size": 1580,
                      "lmtime": 0,
                      "modified": false
                    },
                    "category.svg": {
                      "type": "-",
                      "size": 2117,
                      "lmtime": 0,
                      "modified": false
                    },
                    "chart.svg": {
                      "type": "-",
                      "size": 179,
                      "lmtime": 0,
                      "modified": false
                    },
                    "clipboard.svg": {
                      "type": "-",
                      "size": 971,
                      "lmtime": 0,
                      "modified": false
                    },
                    "codeowners.svg": {
                      "type": "-",
                      "size": 908,
                      "lmtime": 0,
                      "modified": false
                    },
                    "comment.svg": {
                      "type": "-",
                      "size": 1552,
                      "lmtime": 0,
                      "modified": false
                    },
                    "component.svg": {
                      "type": "-",
                      "size": 319,
                      "lmtime": 0,
                      "modified": false
                    },
                    "create-user.svg": {
                      "type": "-",
                      "size": 1131,
                      "lmtime": 0,
                      "modified": false
                    },
                    "dashboard.svg": {
                      "type": "-",
                      "size": 2335,
                      "lmtime": 0,
                      "modified": false
                    },
                    "documentation.svg": {
                      "type": "-",
                      "size": 418,
                      "lmtime": 0,
                      "modified": false
                    },
                    "dollar.svg": {
                      "type": "-",
                      "size": 2229,
                      "lmtime": 0,
                      "modified": false
                    },
                    "drag.svg": {
                      "type": "-",
                      "size": 356,
                      "lmtime": 0,
                      "modified": false
                    },
                    "edit.svg": {
                      "type": "-",
                      "size": 818,
                      "lmtime": 0,
                      "modified": false
                    },
                    "education.svg": {
                      "type": "-",
                      "size": 1068,
                      "lmtime": 0,
                      "modified": false
                    },
                    "email.svg": {
                      "type": "-",
                      "size": 347,
                      "lmtime": 0,
                      "modified": false
                    },
                    "example.svg": {
                      "type": "-",
                      "size": 497,
                      "lmtime": 0,
                      "modified": false
                    },
                    "excel.svg": {
                      "type": "-",
                      "size": 459,
                      "lmtime": 0,
                      "modified": false
                    },
                    "exit-fullscreen.svg": {
                      "type": "-",
                      "size": 1803,
                      "lmtime": 0,
                      "modified": false
                    },
                    "eye-open.svg": {
                      "type": "-",
                      "size": 1290,
                      "lmtime": 0,
                      "modified": false
                    },
                    "eye.svg": {
                      "type": "-",
                      "size": 944,
                      "lmtime": 0,
                      "modified": false
                    },
                    "form.svg": {
                      "type": "-",
                      "size": 2494,
                      "lmtime": 0,
                      "modified": false
                    },
                    "fullscreen.svg": {
                      "type": "-",
                      "size": 421,
                      "lmtime": 0,
                      "modified": false
                    },
                    "guide 2.svg": {
                      "type": "-",
                      "size": 377,
                      "lmtime": 0,
                      "modified": false
                    },
                    "guide.svg": {
                      "type": "-",
                      "size": 320,
                      "lmtime": 0,
                      "modified": false
                    },
                    "humans.svg": {
                      "type": "-",
                      "size": 1407,
                      "lmtime": 0,
                      "modified": false
                    },
                    "icon.svg": {
                      "type": "-",
                      "size": 1076,
                      "lmtime": 0,
                      "modified": false
                    },
                    "international.svg": {
                      "type": "-",
                      "size": 1117,
                      "lmtime": 0,
                      "modified": false
                    },
                    "language.svg": {
                      "type": "-",
                      "size": 1259,
                      "lmtime": 0,
                      "modified": false
                    },
                    "layout.svg": {
                      "type": "-",
                      "size": 641,
                      "lmtime": 0,
                      "modified": false
                    },
                    "lead.svg": {
                      "type": "-",
                      "size": 1349,
                      "lmtime": 0,
                      "modified": false
                    },
                    "like.svg": {
                      "type": "-",
                      "size": 1253,
                      "lmtime": 0,
                      "modified": false
                    },
                    "link.svg": {
                      "type": "-",
                      "size": 285,
                      "lmtime": 0,
                      "modified": false
                    },
                    "list.svg": {
                      "type": "-",
                      "size": 1017,
                      "lmtime": 0,
                      "modified": false
                    },
                    "lock.svg": {
                      "type": "-",
                      "size": 444,
                      "lmtime": 0,
                      "modified": false
                    },
                    "magic.svg": {
                      "type": "-",
                      "size": 1240,
                      "lmtime": 0,
                      "modified": false
                    },
                    "management.svg": {
                      "type": "-",
                      "size": 2343,
                      "lmtime": 0,
                      "modified": false
                    },
                    "message.svg": {
                      "type": "-",
                      "size": 669,
                      "lmtime": 0,
                      "modified": false
                    },
                    "money.svg": {
                      "type": "-",
                      "size": 335,
                      "lmtime": 0,
                      "modified": false
                    },
                    "nested.svg": {
                      "type": "-",
                      "size": 821,
                      "lmtime": 0,
                      "modified": false
                    },
                    "password.svg": {
                      "type": "-",
                      "size": 623,
                      "lmtime": 0,
                      "modified": false
                    },
                    "paw.svg": {
                      "type": "-",
                      "size": 1854,
                      "lmtime": 0,
                      "modified": false
                    },
                    "pdf.svg": {
                      "type": "-",
                      "size": 1714,
                      "lmtime": 0,
                      "modified": false
                    },
                    "people.svg": {
                      "type": "-",
                      "size": 1207,
                      "lmtime": 0,
                      "modified": false
                    },
                    "peoples.svg": {
                      "type": "-",
                      "size": 731,
                      "lmtime": 0,
                      "modified": false
                    },
                    "permission.svg": {
                      "type": "-",
                      "size": 1120,
                      "lmtime": 1592602613468,
                      "modified": false
                    },
                    "permissions.svg": {
                      "type": "-",
                      "size": 1830,
                      "lmtime": 1592602467037,
                      "modified": false
                    },
                    "pets.svg": {
                      "type": "-",
                      "size": 1663,
                      "lmtime": 0,
                      "modified": false
                    },
                    "qq.svg": {
                      "type": "-",
                      "size": 3675,
                      "lmtime": 0,
                      "modified": false
                    },
                    "role.svg": {
                      "type": "-",
                      "size": 987,
                      "lmtime": 0,
                      "modified": false
                    },
                    "search.svg": {
                      "type": "-",
                      "size": 600,
                      "lmtime": 0,
                      "modified": false
                    },
                    "setting.svg": {
                      "type": "-",
                      "size": 1352,
                      "lmtime": 1592602062079,
                      "modified": false
                    },
                    "shopping.svg": {
                      "type": "-",
                      "size": 2236,
                      "lmtime": 0,
                      "modified": false
                    },
                    "size.svg": {
                      "type": "-",
                      "size": 211,
                      "lmtime": 0,
                      "modified": false
                    },
                    "skill.svg": {
                      "type": "-",
                      "size": 1777,
                      "lmtime": 0,
                      "modified": false
                    },
                    "star.svg": {
                      "type": "-",
                      "size": 563,
                      "lmtime": 0,
                      "modified": false
                    },
                    "tab.svg": {
                      "type": "-",
                      "size": 655,
                      "lmtime": 0,
                      "modified": false
                    },
                    "table.svg": {
                      "type": "-",
                      "size": 597,
                      "lmtime": 0,
                      "modified": false
                    },
                    "task-list.svg": {
                      "type": "-",
                      "size": 1219,
                      "lmtime": 1592602394661,
                      "modified": false
                    },
                    "task.svg": {
                      "type": "-",
                      "size": 914,
                      "lmtime": 0,
                      "modified": false
                    },
                    "tasks.svg": {
                      "type": "-",
                      "size": 1219,
                      "lmtime": 0,
                      "modified": false
                    },
                    "theme.svg": {
                      "type": "-",
                      "size": 689,
                      "lmtime": 0,
                      "modified": false
                    },
                    "todo.svg": {
                      "type": "-",
                      "size": 725,
                      "lmtime": 0,
                      "modified": false
                    },
                    "tree-table.svg": {
                      "type": "-",
                      "size": 906,
                      "lmtime": 0,
                      "modified": false
                    },
                    "tree.svg": {
                      "type": "-",
                      "size": 1814,
                      "lmtime": 0,
                      "modified": false
                    },
                    "user.svg": {
                      "type": "-",
                      "size": 440,
                      "lmtime": 0,
                      "modified": false
                    },
                    "user_role.svg": {
                      "type": "-",
                      "size": 2142,
                      "lmtime": 1592603042348,
                      "modified": false
                    },
                    "wechat.svg": {
                      "type": "-",
                      "size": 1173,
                      "lmtime": 0,
                      "modified": false
                    },
                    "zip.svg": {
                      "type": "-",
                      "size": 1460,
                      "lmtime": 0,
                      "modified": false
                    }
                  },
                  "svgo.yml": {
                    "type": "-",
                    "size": 248,
                    "lmtime": 0,
                    "modified": false
                  }
                },
                "lang": {
                  "_notes": {},
                  "en.js": {
                    "type": "-",
                    "size": 9980,
                    "lmtime": 1592705548535,
                    "modified": false
                  },
                  "index.js": {
                    "type": "-",
                    "size": 1047,
                    "lmtime": 0,
                    "modified": false
                  },
                  "pt_BR.js": {
                    "type": "-",
                    "size": 10049,
                    "lmtime": 1592706581637,
                    "modified": false
                  }
                },
                "layout": {},
                "permission.js": {
                  "type": "-",
                  "size": 2582,
                  "lmtime": 0,
                  "modified": false
                },
                "router": {
                  ".DS_Store": {
                    "type": "-",
                    "size": 6148,
                    "lmtime": 0,
                    "modified": false
                  },
                  "_notes": {},
                  "index.js": {
                    "type": "-",
                    "size": 3510,
                    "lmtime": 1592603862688,
                    "modified": false
                  },
                  "modules": {
                    "_notes": {},
                    "admin.js": {
                      "type": "-",
                      "size": 1678,
                      "lmtime": 1592603010011,
                      "modified": false
                    },
                    "charts.js": {
                      "type": "-",
                      "size": 876,
                      "lmtime": 0,
                      "modified": false
                    },
                    "cms.js": {
                      "type": "-",
                      "size": 767,
                      "lmtime": 0,
                      "modified": false
                    },
                    "components.js": {
                      "type": "-",
                      "size": 2784,
                      "lmtime": 0,
                      "modified": false
                    },
                    "crm.js": {
                      "type": "-",
                      "size": 1078,
                      "lmtime": 0,
                      "modified": false
                    },
                    "element-ui.js": {
                      "type": "-",
                      "size": 774,
                      "lmtime": 0,
                      "modified": false
                    },
                    "error.js": {
                      "type": "-",
                      "size": 651,
                      "lmtime": 0,
                      "modified": false
                    },
                    "example.js": {
                      "type": "-",
                      "size": 876,
                      "lmtime": 0,
                      "modified": false
                    },
                    "excel.js": {
                      "type": "-",
                      "size": 1048,
                      "lmtime": 0,
                      "modified": false
                    },
                    "nested.js": {
                      "type": "-",
                      "size": 1715,
                      "lmtime": 0,
                      "modified": false
                    },
                    "permission.js": {
                      "type": "-",
                      "size": 868,
                      "lmtime": 1592602637415,
                      "modified": false
                    },
                    "productivity.js": {
                      "type": "-",
                      "size": 745,
                      "lmtime": 1592602337178,
                      "modified": false
                    },
                    "settings.js": {
                      "type": "-",
                      "size": 665,
                      "lmtime": 1592601029958,
                      "modified": false
                    },
                    "table.js": {
                      "type": "-",
                      "size": 1176,
                      "lmtime": 0,
                      "modified": false
                    }
                  }
                },
                "settings.js": {
                  "type": "-",
                  "size": 950,
                  "lmtime": 0,
                  "modified": false
                },
                "store": {},
                "styles": {},
                "utils": {},
                "vendor": {},
                "views": {
                  "cms": {
                    "posts": {
                      "List.vue": {
                        "type": "-",
                        "size": 13962,
                        "lmtime": 1592706399094,
                        "modified": false
                      },
                      "_notes": {}
                    }
                  },
                  "crm": {
                    "wizard": {
                      "_notes": {},
                      "wizard.vue": {
                        "type": "-",
                        "size": 13973,
                        "lmtime": 1592761052257,
                        "modified": false
                      }
                    }
                  }
                }
              }
            },
            "routes": {},
            "server.php": {
              "type": "-",
              "size": 563,
              "lmtime": 0,
              "modified": false
            },
            "storage": {
              "framework": {
                "sessions": {
                  ".gitignore": {
                    "type": "-",
                    "size": 14,
                    "lmtime": 0,
                    "modified": false
                  },
                  "G9e8TTkdpA1SPcvVYEtfrUcV61yOvqXtGJQJycBs": {
                    "type": "-",
                    "size": 190,
                    "lmtime": 0,
                    "modified": false
                  },
                  "KK00dKnB7ZVLhOSCLGxXeqnaDOAmwNsnikN3WSsv": {
                    "type": "-",
                    "size": 179,
                    "lmtime": 1592711715478,
                    "modified": false
                  },
                  "LiHkhDyoW5Qg6IRrKZoNaDntNdsCfkjiRipHvTMd": {
                    "type": "-",
                    "size": 190,
                    "lmtime": 0,
                    "modified": false
                  },
                  "Ol5wUxKvhh2WKMthpnG5MaPOr2VzWUNAsBrwYRA0": {
                    "type": "-",
                    "size": 190,
                    "lmtime": 0,
                    "modified": false
                  },
                  "Ta0TTEZbdXdxZvfwbrKw6mgCI2mmVa8SrmrzyJUq": {
                    "type": "-",
                    "size": 190,
                    "lmtime": 0,
                    "modified": false
                  },
                  "aICoYfFHNxX4zsROW9ibun95OvK54Sdaq9TBJ3zI": {
                    "type": "-",
                    "size": 190,
                    "lmtime": 0,
                    "modified": false
                  },
                  "aWWWCdPD8Olc8W5dvJ3w8gjZMn5ywgs51nxZJBqf": {
                    "type": "-",
                    "size": 190,
                    "lmtime": 0,
                    "modified": false
                  },
                  "ar7LxRJwzkGVf66SDoPfreQJDIDiBf3B16PptFbc": {
                    "type": "-",
                    "size": 190,
                    "lmtime": 0,
                    "modified": false
                  },
                  "iWYtY2uE2d3eNnI9S8wbip7HR63PNEFkMmqDTfH2": {
                    "type": "-",
                    "size": 190,
                    "lmtime": 0,
                    "modified": false
                  },
                  "n0sivWVrgGjWX29E6h1Of9Kd2ZnPwH7eozrWoRW8": {
                    "type": "-",
                    "size": 190,
                    "lmtime": 0,
                    "modified": false
                  },
                  "p7PNCurojWCQN8KX34D2LwOvSloTrvtN8GUeJw8i": {
                    "type": "-",
                    "size": 190,
                    "lmtime": 0,
                    "modified": false
                  },
                  "pYWR8omRPQGspHcXiijy10I8nLaCYaL1kov3pgMB": {
                    "type": "-",
                    "size": 190,
                    "lmtime": 0,
                    "modified": false
                  },
                  "xdNb7rtUHOIqsLjfp12w7ep1dT7TuWL7EKaNIzMJ": {
                    "type": "-",
                    "size": 190,
                    "lmtime": 0,
                    "modified": false
                  }
                },
                "cache": {
                  "data": {
                    "13": {},
                    "39": {},
                    "58": {},
                    "76": {
                      "e7": {
                        "76e7c0fdd0cc0d46502f9d381b947cdf6aa69891": {
                          "type": "-",
                          "size": 23,
                          "lmtime": 1592711672805,
                          "modified": false
                        }
                      }
                    },
                    "85": {
                      "5f": {
                        "855f92484c8c414d36c1b25cb24876e30229cbbf": {
                          "type": "-",
                          "size": 140700,
                          "lmtime": 1592602668869,
                          "modified": false
                        }
                      }
                    },
                    ".gitignore": {
                      "type": "-",
                      "size": 14,
                      "lmtime": 0,
                      "modified": false
                    },
                    "06": {},
                    "0e": {},
                    "0f": {},
                    "2f": {},
                    "3f": {},
                    "7a": {},
                    "7d": {
                      "36": {
                        "7d36ab8afcb59632bc9f122f17e545d682de6b25": {
                          "type": "-",
                          "size": 23,
                          "lmtime": 1592711671484,
                          "modified": false
                        }
                      }
                    },
                    "9c": {
                      "1c": {
                        "9c1c01dc3ac1445a500251fc34a15d3e75a849df": {
                          "type": "-",
                          "size": 14,
                          "lmtime": 1592711717844,
                          "modified": false
                        }
                      }
                    },
                    "ac": {},
                    "b4": {},
                    "bc": {
                      "11": {
                        "bc11d69cd41accb36b5cccc6ec42558ab95cbfe0": {
                          "type": "-",
                          "size": 14,
                          "lmtime": 1592711671485,
                          "modified": false
                        }
                      }
                    },
                    "d0": {},
                    "d9": {},
                    "db": {},
                    "f7": {
                      "49": {
                        "f74914c7e07c9294479cdd4d1d13e397d8ac4d4f": {
                          "type": "-",
                          "size": 48,
                          "lmtime": 1592606556733,
                          "modified": false
                        }
                      }
                    }
                  }
                }
              },
              "debugbar": {
                ".gitignore": {
                  "type": "-",
                  "size": 14,
                  "lmtime": 0,
                  "modified": false
                },
                "X00b943ccbc4308e658676521c52ba547.json": {
                  "type": "-",
                  "size": 24735,
                  "lmtime": 1592694100501,
                  "modified": false
                },
                "X0490b3028a72c83214e1c39f6e32649e.json": {
                  "type": "-",
                  "size": 28986,
                  "lmtime": 1592706533017,
                  "modified": false
                },
                "X054fbe715d711d1fff612e4804ebd343.json": {
                  "type": "-",
                  "size": 28950,
                  "lmtime": 1592705634719,
                  "modified": false
                },
                "X058d08df59f78e59aac3c247b38aafd0.json": {
                  "type": "-",
                  "size": 24550,
                  "lmtime": 1592695094426,
                  "modified": false
                },
                "X05bf21b373ea59683aa4f00caf58fd71.json": {
                  "type": "-",
                  "size": 32249,
                  "lmtime": 1592711672326,
                  "modified": false
                },
                "X0645a49f1a30177e17fd7b2c6e93c603.json": {
                  "type": "-",
                  "size": 16766,
                  "lmtime": 1592693649428,
                  "modified": false
                },
                "X07dca6f6e7425e6db20f485ee10c0405.json": {
                  "type": "-",
                  "size": 49114,
                  "lmtime": 0,
                  "modified": false
                },
                "X08a0032d8dbfdbb7595f4c0a822265df.json": {
                  "type": "-",
                  "size": 32947,
                  "lmtime": 1592693234924,
                  "modified": false
                },
                "X0aa04172db764b38fca4535d56f9bc2e.json": {
                  "type": "-",
                  "size": 24488,
                  "lmtime": 1592692620618,
                  "modified": false
                },
                "X0e9b6cf9b51d4770ee4a8c74240acaa7.json": {
                  "type": "-",
                  "size": 32946,
                  "lmtime": 1592694751354,
                  "modified": false
                },
                "X0f34bd5ab281ed949f94542fdfc264a7.json": {
                  "type": "-",
                  "size": 28827,
                  "lmtime": 1592693612416,
                  "modified": false
                },
                "X10ffad62903d8cfe9ddae5ffbee2a4c3.json": {
                  "type": "-",
                  "size": 28825,
                  "lmtime": 1592694101201,
                  "modified": false
                },
                "X111fc36f8990e7e5a17dc81d60baa6a0.json": {
                  "type": "-",
                  "size": 40142,
                  "lmtime": 0,
                  "modified": false
                },
                "X13694c33255fa382a983da448003ca2d.json": {
                  "type": "-",
                  "size": 14485,
                  "lmtime": 0,
                  "modified": false
                },
                "X14d3f268c290dbb83e4f35f84247a1c7.json": {
                  "type": "-",
                  "size": 22163,
                  "lmtime": 0,
                  "modified": false
                },
                "X171bbcc86fd0a0515aa4a49272688cb1.json": {
                  "type": "-",
                  "size": 32936,
                  "lmtime": 1592695444982,
                  "modified": false
                },
                "X1887c582648e4da4bb9502c9c2abc7f4.json": {
                  "type": "-",
                  "size": 24737,
                  "lmtime": 1592693612356,
                  "modified": false
                },
                "X1d60d80132152ead7760a6d5e9fa392f.json": {
                  "type": "-",
                  "size": 16759,
                  "lmtime": 1592694096119,
                  "modified": false
                },
                "X1deca32f956c59793200d39996addc28.json": {
                  "type": "-",
                  "size": 16862,
                  "lmtime": 1592711696069,
                  "modified": false
                },
                "X1eba7f2f28d5e762481eee655bb3b975.json": {
                  "type": "-",
                  "size": 33090,
                  "lmtime": 1592705634160,
                  "modified": false
                },
                "X1fbedbe6f7654a5f65d3738c55adde07.json": {
                  "type": "-",
                  "size": 28842,
                  "lmtime": 1592695393049,
                  "modified": false
                },
                "X239c9206ede695af9b22f394d1a3ea4f.json": {
                  "type": "-",
                  "size": 24785,
                  "lmtime": 1592694898091,
                  "modified": false
                },
                "X241da73fafd4c2bf84049ab296290872.json": {
                  "type": "-",
                  "size": 28971,
                  "lmtime": 1592711698279,
                  "modified": false
                },
                "X24ee3a2f900cc1d294354c3bf9379272.json": {
                  "type": "-",
                  "size": 16866,
                  "lmtime": 1592711715493,
                  "modified": false
                },
                "X25d8ef8148c0840b50b8522b3b61e4b3.json": {
                  "type": "-",
                  "size": 22317,
                  "lmtime": 0,
                  "modified": false
                },
                "X288615c4f1c70c8ade1b8f529a24b57c.json": {
                  "type": "-",
                  "size": 25961,
                  "lmtime": 0,
                  "modified": false
                },
                "X290f1e431ec9a3ce43672737f9f4aac5.json": {
                  "type": "-",
                  "size": 16761,
                  "lmtime": 1592695323420,
                  "modified": false
                },
                "X297e33d5482cf00523ab24b6123061b5.json": {
                  "type": "-",
                  "size": 24870,
                  "lmtime": 1592711698225,
                  "modified": false
                },
                "X29e5ec45e889d547c221bc9b13a4a906.json": {
                  "type": "-",
                  "size": 28811,
                  "lmtime": 1592693235503,
                  "modified": false
                },
                "X2dd099273bc78b28fd4dbaf7b6fe00bb.json": {
                  "type": "-",
                  "size": 24482,
                  "lmtime": 1592695094770,
                  "modified": false
                },
                "X2e9741205ce6d4a362db204e9a1cf023.json": {
                  "type": "-",
                  "size": 16320,
                  "lmtime": 1592692616062,
                  "modified": false
                },
                "X2ee5f82b29279fcfeed2fdd20d7b0d28.json": {
                  "type": "-",
                  "size": 24886,
                  "lmtime": 1592705634678,
                  "modified": false
                },
                "X2fe5d5f73192f425c623074c426c5f1f.json": {
                  "type": "-",
                  "size": 15778,
                  "lmtime": 0,
                  "modified": false
                },
                "X317685ac4b4c2ebe7295a65859ade536.json": {
                  "type": "-",
                  "size": 43305,
                  "lmtime": 0,
                  "modified": false
                },
                "X35e314d0d7b73b8e16f09d531622a3b1.json": {
                  "type": "-",
                  "size": 25014,
                  "lmtime": 1592672395757,
                  "modified": false
                },
                "X35ff4007430aef9307590feeaa41d6f7.json": {
                  "type": "-",
                  "size": 28822,
                  "lmtime": 1592694152875,
                  "modified": false
                },
                "X39be6a2aed24404bc583332aa29f6cc2.json": {
                  "type": "-",
                  "size": 16877,
                  "lmtime": 1592705632679,
                  "modified": false
                },
                "X3a2196825621af35fb48d425d18c02da.json": {
                  "type": "-",
                  "size": 20673,
                  "lmtime": 1592695094404,
                  "modified": false
                },
                "X3bc1e61ec5ceae570ff895dbdac9cf8c.json": {
                  "type": "-",
                  "size": 28850,
                  "lmtime": 1592694751995,
                  "modified": false
                },
                "X3c142490125502098ae4fc931bc0a80b.json": {
                  "type": "-",
                  "size": 15022,
                  "lmtime": 1592692614830,
                  "modified": false
                },
                "X3c826e9ed9284fa5c6db74b51b312e2b.json": {
                  "type": "-",
                  "size": 34756,
                  "lmtime": 0,
                  "modified": false
                },
                "X3ccf82551ada103e581c3b29214118ee.json": {
                  "type": "-",
                  "size": 24752,
                  "lmtime": 1592692626971,
                  "modified": false
                },
                "X3d4483a8786c8ffe02aa81c5e7961bbf.json": {
                  "type": "-",
                  "size": 34609,
                  "lmtime": 0,
                  "modified": false
                },
                "X3defdf29eb0b0edad8219a3606d94127.json": {
                  "type": "-",
                  "size": 28809,
                  "lmtime": 1592695445840,
                  "modified": false
                },
                "X456514635c900e891cb7ec6c0db1e0c4.json": {
                  "type": "-",
                  "size": 28843,
                  "lmtime": 1592695325683,
                  "modified": false
                },
                "X4dfcddf94331a51493acc6bd073e15f7.json": {
                  "type": "-",
                  "size": 34093,
                  "lmtime": 0,
                  "modified": false
                },
                "X4ff69e6f4f65dbd62a08ee62286d5dc9.json": {
                  "type": "-",
                  "size": 16755,
                  "lmtime": 1592693233245,
                  "modified": false
                },
                "X5004fd2796910578fb9a027abc4d3cdb.json": {
                  "type": "-",
                  "size": 24481,
                  "lmtime": 1592692620226,
                  "modified": false
                },
                "X507ec3e9947014c2b892682e465053b5.json": {
                  "type": "-",
                  "size": 24733,
                  "lmtime": 1592693651228,
                  "modified": false
                },
                "X52e3b3000ce9301fdcdf05fe0bb74130.json": {
                  "type": "-",
                  "size": 32934,
                  "lmtime": 1592694099232,
                  "modified": false
                },
                "X5351572986113155231aec25b4dba00a.json": {
                  "type": "-",
                  "size": 25939,
                  "lmtime": 0,
                  "modified": false
                },
                "X53c6be8e080a1ee493112691203d4e02.json": {
                  "type": "-",
                  "size": 32944,
                  "lmtime": 1592695325024,
                  "modified": false
                },
                "X5445627c7a0bbc0b535288901bd83d98.json": {
                  "type": "-",
                  "size": 25967,
                  "lmtime": 0,
                  "modified": false
                },
                "X55531696e4cfc70ad879f4eb5eb0990a.json": {
                  "type": "-",
                  "size": 24762,
                  "lmtime": 1592694751947,
                  "modified": false
                },
                "X560d9b3429c721620c40cab1c65333c7.json": {
                  "type": "-",
                  "size": 34230,
                  "lmtime": 0,
                  "modified": false
                },
                "X5627246995b6099b6979cefd0a39df3f.json": {
                  "type": "-",
                  "size": 32943,
                  "lmtime": 1592692619063,
                  "modified": false
                },
                "X57fd2da615d2e47d7f6ebce0155e65c6.json": {
                  "type": "-",
                  "size": 32136,
                  "lmtime": 1592702839985,
                  "modified": false
                },
                "X59b10e9fd3cf02754c9cf12e88e0d02e.json": {
                  "type": "-",
                  "size": 32112,
                  "lmtime": 1592692618647,
                  "modified": false
                },
                "X5ce34a03e04123f1ac31061da3183a47.json": {
                  "type": "-",
                  "size": 16453,
                  "lmtime": 1592706530098,
                  "modified": false
                },
                "X5e1ebf576e790bb4f713875ca2bb488f.json": {
                  "type": "-",
                  "size": 33074,
                  "lmtime": 1592711697624,
                  "modified": false
                },
                "X5ea8494eb363d2a366d76f582dc5aea4.json": {
                  "type": "-",
                  "size": 14583,
                  "lmtime": 0,
                  "modified": false
                },
                "X5eeee97ef4503e97ad74b1e009d9eeb2.json": {
                  "type": "-",
                  "size": 33094,
                  "lmtime": 1592706532480,
                  "modified": false
                },
                "X62c33dd509e7cd0c3ba4548086e0417f.json": {
                  "type": "-",
                  "size": 16871,
                  "lmtime": 1592706431109,
                  "modified": false
                },
                "X6489ca8e092f5ba92092f85a0edb2718.json": {
                  "type": "-",
                  "size": 14578,
                  "lmtime": 0,
                  "modified": false
                },
                "X662a51625b1900acfb22b7ea30cde57c.json": {
                  "type": "-",
                  "size": 28962,
                  "lmtime": 1592711673764,
                  "modified": false
                },
                "X6941ced633d43d3ff58f5e061f961d26.json": {
                  "type": "-",
                  "size": 32948,
                  "lmtime": 1592694897344,
                  "modified": false
                },
                "X69ea7d4d56eb1c0ae61c182ee2db0ee0.json": {
                  "type": "-",
                  "size": 33061,
                  "lmtime": 1592711717070,
                  "modified": false
                },
                "X69f302a1a3c34157d97c40abc46d2508.json": {
                  "type": "-",
                  "size": 16749,
                  "lmtime": 1592695442645,
                  "modified": false
                },
                "X6a3c62ab479f91d0917d5ae74857278f.json": {
                  "type": "-",
                  "size": 24531,
                  "lmtime": 1592692619845,
                  "modified": false
                },
                "X6a44be94fef8b93a69be2dd6dbed9f0d.json": {
                  "type": "-",
                  "size": 34011,
                  "lmtime": 0,
                  "modified": false
                },
                "X6b1943d3e8d31a12e3fad68e58d3d18b.json": {
                  "type": "-",
                  "size": 24743,
                  "lmtime": 1592695141205,
                  "modified": false
                },
                "X6b863ac057aa36b84801251ee8852ead.json": {
                  "type": "-",
                  "size": 26040,
                  "lmtime": 0,
                  "modified": false
                },
                "X6cc5eb400d5143d926ffdd4d435e0b8d.json": {
                  "type": "-",
                  "size": 16379,
                  "lmtime": 1592695092252,
                  "modified": false
                },
                "X6f89a3cd028ab71dc71d82e0fc6a8a85.json": {
                  "type": "-",
                  "size": 24890,
                  "lmtime": 1592706532975,
                  "modified": false
                },
                "X703aaebbb0ffd21a8faceaac566bae2b.json": {
                  "type": "-",
                  "size": 16459,
                  "lmtime": 1592711669585,
                  "modified": false
                },
                "X707bef9cb5505a0ed51d90fccafed09f.json": {
                  "type": "-",
                  "size": 30461,
                  "lmtime": 0,
                  "modified": false
                },
                "X72a62849358fb2f7659630ca80d31d5b.json": {
                  "type": "-",
                  "size": 16746,
                  "lmtime": 1592694147822,
                  "modified": false
                },
                "X734f2715bff9544c52f682d48ef6fc22.json": {
                  "type": "-",
                  "size": 16756,
                  "lmtime": 1592695138964,
                  "modified": false
                },
                "X75ecc680fa6390e97b718039498706cc.json": {
                  "type": "-",
                  "size": 16761,
                  "lmtime": 1592694894927,
                  "modified": false
                },
                "X77256371bbf688247ddae46005b1fcb9.json": {
                  "type": "-",
                  "size": 33089,
                  "lmtime": 1592706432522,
                  "modified": false
                },
                "X7a7ac0090b5c71aa9c11e6c1055110a9.json": {
                  "type": "-",
                  "size": 22101,
                  "lmtime": 0,
                  "modified": false
                },
                "X7b3286c6e9d4f5c7de9c865d443e0ff6.json": {
                  "type": "-",
                  "size": 32937,
                  "lmtime": 1592693611808,
                  "modified": false
                },
                "X7e8bd06c3836759b5e75f1afad764746.json": {
                  "type": "-",
                  "size": 16869,
                  "lmtime": 1592711668291,
                  "modified": false
                },
                "X7f11793bec0920d7dbd29e6b52b5a995.json": {
                  "type": "-",
                  "size": 25962,
                  "lmtime": 0,
                  "modified": false
                },
                "X7f8fa81a6618842f4d6400d7d62a18ac.json": {
                  "type": "-",
                  "size": 28841,
                  "lmtime": 1592694898174,
                  "modified": false
                },
                "X863419e748d37330c908460d2f365192.json": {
                  "type": "-",
                  "size": 26101,
                  "lmtime": 0,
                  "modified": false
                },
                "X8a6883caccbd54a3283f1a0b3905fdae.json": {
                  "type": "-",
                  "size": 26184,
                  "lmtime": 0,
                  "modified": false
                },
                "X8f4b9cdd2dd242e004943de49d5708e4.json": {
                  "type": "-",
                  "size": 22081,
                  "lmtime": 0,
                  "modified": false
                },
                "X900783db9b3d3459ce8a24d3687a7af1.json": {
                  "type": "-",
                  "size": 35364,
                  "lmtime": 0,
                  "modified": false
                },
                "X922f0c46e68153336002c45b5024237e.json": {
                  "type": "-",
                  "size": 24734,
                  "lmtime": 1592694152727,
                  "modified": false
                },
                "X93649820eea658d476f38fec2a0b6cd6.json": {
                  "type": "-",
                  "size": 17399,
                  "lmtime": 0,
                  "modified": false
                },
                "X9522b9551b26b45ce82338037ae35867.json": {
                  "type": "-",
                  "size": 24734,
                  "lmtime": 1592693235454,
                  "modified": false
                },
                "X97f9430f361a48adb848fc0e8d58d163.json": {
                  "type": "-",
                  "size": 32980,
                  "lmtime": 1592702840380,
                  "modified": false
                },
                "X9917c9ffbb9c47db9eb462a068074377.json": {
                  "type": "-",
                  "size": 24739,
                  "lmtime": 1592695445761,
                  "modified": false
                },
                "X9ddee8e1cb2b481d7889e9cc89f23bb0.json": {
                  "type": "-",
                  "size": 32269,
                  "lmtime": 1592706532077,
                  "modified": false
                },
                "Xa5e9c362147946f603b0f48edd091ee2.json": {
                  "type": "-",
                  "size": 34083,
                  "lmtime": 0,
                  "modified": false
                },
                "Xa87bcea738301dd36ec9fdf73bf5c6a3.json": {
                  "type": "-",
                  "size": 32932,
                  "lmtime": 1592695392495,
                  "modified": false
                },
                "Xa9c93c2fe76d07e70bc5d91ce065d90a.json": {
                  "type": "-",
                  "size": 22175,
                  "lmtime": 0,
                  "modified": false
                },
                "Xaa8a341067f8cba18794f42a7c80dac7.json": {
                  "type": "-",
                  "size": 32931,
                  "lmtime": 1592695093626,
                  "modified": false
                },
                "Xae6bea342befd83913d3b1479551627e.json": {
                  "type": "-",
                  "size": 26195,
                  "lmtime": 0,
                  "modified": false
                },
                "Xb0bdfd19acf08983c1b8db1b8a7ae8ba.json": {
                  "type": "-",
                  "size": 32968,
                  "lmtime": 1592693650719,
                  "modified": false
                },
                "Xb3565c2de62517d81b5ce1b9275524b6.json": {
                  "type": "-",
                  "size": 16750,
                  "lmtime": 1592693610215,
                  "modified": false
                },
                "Xb4512ea1f93873cd551ffc7fb17a96d6.json": {
                  "type": "-",
                  "size": 24889,
                  "lmtime": 1592706433070,
                  "modified": false
                },
                "Xb4f8af5726a48eaa2b6d55ddd595fa00.json": {
                  "type": "-",
                  "size": 16759,
                  "lmtime": 1592695390156,
                  "modified": false
                },
                "Xba5fd7a9e03ef61958b7a249de21128c.json": {
                  "type": "-",
                  "size": 16751,
                  "lmtime": 1592694749944,
                  "modified": false
                },
                "Xbb26650e73dc49aebf421c52b7b5fd49.json": {
                  "type": "-",
                  "size": 28854,
                  "lmtime": 1592695141235,
                  "modified": false
                },
                "Xbb6ae5ea61eaeae2e0d261aa01a11e7b.json": {
                  "type": "-",
                  "size": 16355,
                  "lmtime": 1592702837817,
                  "modified": false
                },
                "Xbf1d17d2c679e8bd09519b69f9a2aba2.json": {
                  "type": "-",
                  "size": 28820,
                  "lmtime": 1592695099029,
                  "modified": false
                },
                "Xc0a4748fa259061b33021a4db247502c.json": {
                  "type": "-",
                  "size": 16782,
                  "lmtime": 1592702931216,
                  "modified": false
                },
                "Xc1ee74b49cbf1c8152815c9358f82145.json": {
                  "type": "-",
                  "size": 24774,
                  "lmtime": 1592702840892,
                  "modified": false
                },
                "Xc4196a559f2c5bad76b2accf75981f68.json": {
                  "type": "-",
                  "size": 26024,
                  "lmtime": 0,
                  "modified": false
                },
                "Xc5cbb1e6e35055ec51d4bdeb0c93343a.json": {
                  "type": "-",
                  "size": 24882,
                  "lmtime": 1592711673682,
                  "modified": false
                },
                "Xd38cdbd9d303682ea813dbe5b4f00b44.json": {
                  "type": "-",
                  "size": 34525,
                  "lmtime": 0,
                  "modified": false
                },
                "Xd5259600c9382149a4f824968be8674f.json": {
                  "type": "-",
                  "size": 20679,
                  "lmtime": 1592692619827,
                  "modified": false
                },
                "Xd531edcce8f30a76a7c54ef22e194040.json": {
                  "type": "-",
                  "size": 17712,
                  "lmtime": 0,
                  "modified": false
                },
                "Xd5fe5d0318e34f8e5e0d088d609bedad.json": {
                  "type": "-",
                  "size": 24736,
                  "lmtime": 1592695393004,
                  "modified": false
                },
                "Xd67b60ff386529c5a600cf4b63c5af00.json": {
                  "type": "-",
                  "size": 24716,
                  "lmtime": 1592695098979,
                  "modified": false
                },
                "Xd81f4a0436cc3a4b5ae2f90ac5f1154e.json": {
                  "type": "-",
                  "size": 29005,
                  "lmtime": 1592706433112,
                  "modified": false
                },
                "Xd889152bf6e8563ad4fa7f52888c5568.json": {
                  "type": "-",
                  "size": 28838,
                  "lmtime": 1592693651267,
                  "modified": false
                },
                "Xd8bdd78501ba2cd25df02129a71f21e2.json": {
                  "type": "-",
                  "size": 26051,
                  "lmtime": 0,
                  "modified": false
                },
                "Xd9c71e64822cd2944b10124a291e9b4d.json": {
                  "type": "-",
                  "size": 28849,
                  "lmtime": 1592702840937,
                  "modified": false
                },
                "Xda49e49974b62b875088ea770e7d3c04.json": {
                  "type": "-",
                  "size": 48467,
                  "lmtime": 0,
                  "modified": false
                },
                "Xdc41197dbb6ebcb0084ae4fae70e4946.json": {
                  "type": "-",
                  "size": 32945,
                  "lmtime": 1592694151574,
                  "modified": false
                },
                "Xdd72fa237889922a510c6eeb6c9980d7.json": {
                  "type": "-",
                  "size": 28845,
                  "lmtime": 1592692626999,
                  "modified": false
                },
                "Xde2ac559cdc4834734690b5f4116f21d.json": {
                  "type": "-",
                  "size": 33076,
                  "lmtime": 1592711672941,
                  "modified": false
                },
                "Xe52297cfc3f69613120e6a7ed84c62f7.json": {
                  "type": "-",
                  "size": 34521,
                  "lmtime": 0,
                  "modified": false
                },
                "Xe6127fd04deb4512a8117820e068208b.json": {
                  "type": "-",
                  "size": 15409,
                  "lmtime": 1592702836547,
                  "modified": false
                },
                "Xe70b59c8b82c00e3ac2a3f30bf7f662d.json": {
                  "type": "-",
                  "size": 34103,
                  "lmtime": 0,
                  "modified": false
                },
                "Xea92510b3fa89a290fc77dd80575cd6e.json": {
                  "type": "-",
                  "size": 26056,
                  "lmtime": 0,
                  "modified": false
                },
                "Xeb2155927f0287cf7b7ea99e85b752b9.json": {
                  "type": "-",
                  "size": 32947,
                  "lmtime": 1592702932687,
                  "modified": false
                },
                "Xf30a17ecdaf20d5fe8ce592b7d44139a.json": {
                  "type": "-",
                  "size": 24727,
                  "lmtime": 1592702933211,
                  "modified": false
                },
                "Xf4fd5d6521bd62f56a7c4ad22b117ccf.json": {
                  "type": "-",
                  "size": 34605,
                  "lmtime": 0,
                  "modified": false
                },
                "Xf5c25e31db6ce492dc701d0654f89028.json": {
                  "type": "-",
                  "size": 32938,
                  "lmtime": 1592695140684,
                  "modified": false
                },
                "Xf736689bf2af689e470772b08d458527.json": {
                  "type": "-",
                  "size": 28833,
                  "lmtime": 1592702933274,
                  "modified": false
                },
                "Xf8c14b69a79f3c2c36d8316e8e6052b0.json": {
                  "type": "-",
                  "size": 24750,
                  "lmtime": 1592695325627,
                  "modified": false
                },
                "Xfdc45b1a83e3d2519d80d890eb099168.json": {
                  "type": "-",
                  "size": 24470,
                  "lmtime": 1592695095110,
                  "modified": false
                },
                "Xffa2416ce1a9497d8fd73ceb7630f169.json": {
                  "type": "-",
                  "size": 16873,
                  "lmtime": 1592706528838,
                  "modified": false
                },
                "Xc1d1d105f0c8d072d9620e316d685e43.json": {
                  "type": "-",
                  "size": 24855,
                  "lmtime": 1592711717917,
                  "modified": false
                },
                "Xb68889dd1312ada21b3ef464d9aaeb00.json": {
                  "type": "-",
                  "size": 28957,
                  "lmtime": 1592711717981,
                  "modified": false
                }
              },
              "logs": {
                ".DS_Store": {
                  "type": "-",
                  "size": 6148,
                  "lmtime": 0,
                  "modified": false
                },
                ".gitignore": {
                  "type": "-",
                  "size": 14,
                  "lmtime": 0,
                  "modified": false
                },
                "laravel-2020-02-27.log": {
                  "type": "-",
                  "size": 29660,
                  "lmtime": 0,
                  "modified": false
                },
                "laravel-2020-03-04.log": {
                  "type": "-",
                  "size": 160155,
                  "lmtime": 0,
                  "modified": false
                },
                "laravel-2020-03-05.log": {
                  "type": "-",
                  "size": 437687,
                  "lmtime": 0,
                  "modified": false
                },
                "laravel-2020-03-11.log": {
                  "type": "-",
                  "size": 629791,
                  "lmtime": 0,
                  "modified": false
                },
                "laravel-2020-03-13.log": {
                  "type": "-",
                  "size": 18656,
                  "lmtime": 0,
                  "modified": false
                },
                "laravel-2020-06-12.log": {
                  "type": "-",
                  "size": 138953,
                  "lmtime": 0,
                  "modified": false
                },
                "laravel-2020-06-19.log": {
                  "type": "-",
                  "size": 23240,
                  "lmtime": 0,
                  "modified": false
                },
                "laravel-2020-06-20.log": {
                  "type": "-",
                  "size": 539361,
                  "lmtime": 1592624779344,
                  "modified": false
                }
              }
            },
            "tests": {},
            "vendor": {},
            "webpack.config.js": {
              "type": "-",
              "size": 896,
              "lmtime": 0,
              "modified": false
            },
            "webpack.mix.js": {
              "type": "-",
              "size": 1646,
              "lmtime": 0,
              "modified": false
            },
            "yarn.lock": {
              "type": "-",
              "size": 411837,
              "lmtime": 0,
              "modified": false
            }
          }
        }
      }
    }
  },
  "$version": 1
}